odoo/addons/mail_activity_board/README.rst
odoo/addons/mail_activity_board/__init__.py
odoo/addons/mail_activity_board/__manifest__.py
odoo/addons/mail_activity_board/i18n/de.po
odoo/addons/mail_activity_board/i18n/mail_activity_board.pot
odoo/addons/mail_activity_board/models/__init__.py
odoo/addons/mail_activity_board/models/mail_activity.py
odoo/addons/mail_activity_board/models/mail_activity_mixin.py
odoo/addons/mail_activity_board/readme/CONTRIBUTORS.rst
odoo/addons/mail_activity_board/readme/DESCRIPTION.rst
odoo/addons/mail_activity_board/readme/USAGE.rst
odoo/addons/mail_activity_board/static/description/index.html
odoo/addons/mail_activity_board/static/src/js/override_chatter.js
odoo/addons/mail_activity_board/static/src/xml/inherit_chatter.xml
odoo/addons/mail_activity_board/tests/__init__.py
odoo/addons/mail_activity_board/tests/test_mail_activity_board.py
odoo/addons/mail_activity_board/views/mail_activity_view.xml
odoo/addons/mail_activity_board/views/templates.xml
odoo11_addon_mail_activity_board-11.0.1.0.1.dist-info/METADATA
odoo11_addon_mail_activity_board-11.0.1.0.1.dist-info/RECORD
odoo11_addon_mail_activity_board-11.0.1.0.1.dist-info/WHEEL
odoo11_addon_mail_activity_board-11.0.1.0.1.dist-info/top_level.txt
